facilyst/__init__.py
facilyst/__main__.py
facilyst/version.py
facilyst/graphs/__init__.py
facilyst/graphs/graph_base.py
facilyst/graphs/utils.py
facilyst/graphs/graph_types/__init__.py
facilyst/graphs/graph_types/line.py
facilyst/graphs/graph_types/scatter.py
facilyst/graphs/graph_types/utils.py
facilyst/mocks/__init__.py
facilyst/mocks/mock_base.py
facilyst/mocks/utils.py
facilyst/mocks/mock_types/__init__.py
facilyst/mocks/mock_types/dates.py
facilyst/mocks/mock_types/features.py
facilyst/mocks/mock_types/utils.py
facilyst/mocks/mock_types/wave.py
facilyst/models/__init__.py
facilyst/models/model_base.py
facilyst/models/utils.py
facilyst/models/classifiers/__init__.py
facilyst/models/classifiers/ada_boost.py
facilyst/models/classifiers/bagging.py
facilyst/models/classifiers/catboost.py
facilyst/models/classifiers/decision_tree.py
facilyst/models/classifiers/extra_trees.py
facilyst/models/classifiers/random_forest.py
facilyst/models/classifiers/xgboost.py
facilyst/models/neural_networks/__init__.py
facilyst/models/neural_networks/bert_classifier.py
facilyst/models/neural_networks/bert_qa.py
facilyst/models/neural_networks/mlp_classifier.py
facilyst/models/neural_networks/mlp_regressor.py
facilyst/models/optimizers/__init__.py
facilyst/models/optimizers/hyperopt.py
facilyst/models/regressors/__init__.py
facilyst/models/regressors/ada_boost.py
facilyst/models/regressors/bagging.py
facilyst/models/regressors/catboost.py
facilyst/models/regressors/decision_tree.py
facilyst/models/regressors/extra_trees.py
facilyst/models/regressors/random_forest.py
facilyst/models/regressors/xgboost.py
facilyst/preprocessors/__init__.py
facilyst/preprocessors/preprocessor_base.py
facilyst/preprocessors/datetime/__init__.py
facilyst/preprocessors/datetime/aggregate_datetime.py
facilyst/tests/__init__.py
facilyst/tests/conftest.py
facilyst/tests/test_version.py
facilyst/tests/dataset_tests/__init__.py
facilyst/tests/dataset_tests/test_regression.py
facilyst-0.0.4.dist-info/LICENSE
facilyst-0.0.4.dist-info/METADATA
facilyst-0.0.4.dist-info/WHEEL
facilyst-0.0.4.dist-info/entry_points.txt
facilyst-0.0.4.dist-info/top_level.txt
facilyst-0.0.4.dist-info/RECORD
