Metadata-Version: 2.1
Name: facilyst
Version: 0.0.4
Summary: Make data analysis and machine learning tools more easily accessible.
Home-page: https://github.com/Parthiv-Naresh/facilyst
Author: Parthiv Naresh
Author-email: pnaresh.github@gmail.com
License: MIT License
Project-URL: Source Code, https://github.com/Parthiv-Naresh/facilyst
Keywords: python,machine learning,data science
Platform: UNKNOWN
Classifier: Development Status :: 2 - Pre-Alpha
Classifier: Programming Language :: Python :: 3
Classifier: Programming Language :: Python :: 3.7
Classifier: Programming Language :: Python :: 3.8
Classifier: Programming Language :: Python :: 3.9
Classifier: Programming Language :: Python :: 3.10
Classifier: Intended Audience :: Science/Research
Classifier: Intended Audience :: Developers
Classifier: Topic :: Software Development :: Libraries :: Python Modules
Classifier: Topic :: Scientific/Engineering :: Artificial Intelligence
Classifier: Topic :: Scientific/Engineering :: Image Recognition
Classifier: Topic :: Scientific/Engineering :: Visualization
Classifier: License :: OSI Approved :: MIT License
Requires-Python: <4,>=3.7
License-File: LICENSE
Requires-Dist: numpy (>=1.21.0)
Requires-Dist: pandas (>=1.4.0)
Requires-Dist: scikit-learn (>=0.24.0)
Requires-Dist: matplotlib (>=3.3.3)
Requires-Dist: seaborn (>=0.11.1)
Requires-Dist: click (>=7.1.2)
Requires-Dist: woodwork (>=0.15.0)
Requires-Dist: faker (>=13.3.4)
Requires-Dist: hyperopt (>=0.2.7)
Provides-Extra: dev
Requires-Dist: wheel (>=0.33.1) ; extra == 'dev'
Requires-Dist: setuptools (>=50.0.1) ; extra == 'dev'
Requires-Dist: pytest (==7.0.1) ; extra == 'dev'
Requires-Dist: pytest-xdist (==2.1.0) ; extra == 'dev'
Requires-Dist: pytest-timeout (==2.1.0) ; extra == 'dev'
Requires-Dist: pytest-cov (==2.10.1) ; extra == 'dev'
Requires-Dist: nbval (==0.9.3) ; extra == 'dev'
Requires-Dist: codecov (==2.1.11) ; extra == 'dev'
Requires-Dist: PyYAML (==5.4) ; extra == 'dev'
Requires-Dist: flake8 (==4.0.1) ; extra == 'dev'
Requires-Dist: black (==22.3.0) ; extra == 'dev'
Requires-Dist: isort (==5.0.0) ; extra == 'dev'
Requires-Dist: pydocstyle (==6.1.1) ; extra == 'dev'
Requires-Dist: darglint (==1.8.0) ; extra == 'dev'
Requires-Dist: toml (==0.10.2) ; extra == 'dev'
Requires-Dist: pytype (==2022.4.22) ; extra == 'dev'
Provides-Extra: extra
Requires-Dist: catboost (>=1.0.5) ; extra == 'extra'
Requires-Dist: xgboost (>=1.5.2) ; extra == 'extra'
Requires-Dist: torch (==1.11.0) ; extra == 'extra'
Requires-Dist: transformers (==4.14.1) ; extra == 'extra'
Requires-Dist: sentencepiece (==0.1.95) ; extra == 'extra'
Requires-Dist: Keras-Preprocessing (==1.1.2) ; extra == 'extra'
Provides-Extra: test
Requires-Dist: wheel (>=0.33.1) ; extra == 'test'
Requires-Dist: setuptools (>=50.0.1) ; extra == 'test'
Requires-Dist: pytest (==7.0.1) ; extra == 'test'
Requires-Dist: pytest-xdist (==2.1.0) ; extra == 'test'
Requires-Dist: pytest-timeout (==2.1.0) ; extra == 'test'
Requires-Dist: pytest-cov (==2.10.1) ; extra == 'test'
Requires-Dist: nbval (==0.9.3) ; extra == 'test'
Requires-Dist: codecov (==2.1.11) ; extra == 'test'
Requires-Dist: PyYAML (==5.4) ; extra == 'test'
